gpn_clients/clients/nsi/v1/algorithms.py
gpn_clients/clients/nsi/v1/config.py
gpn_clients/clients/nsi/v1/io_config.py
gpn_clients/clients/nsi/v1/ml_models.py
gpn_clients/clients/nsi/v1/time_series.py
gpn_clients/core/config.py
gpn_clients/models/base_nsi_api.py
gpn_clients/utils/patterns.py
gpn_clients/utils/urls.py
gpn_clients-0.1.2.dist-info/WHEEL
gpn_clients-0.1.2.dist-info/METADATA
gpn_clients-0.1.2.dist-info/RECORD
