Metadata-Version: 2.1
Name: gpn-clients
Version: 0.1.2
Summary: Клиенты для получения данных из источников внутри ГПН
Author: Chumakov Mikhail Dmitrievich
Author-email: i@m-chumakov-dev.ru
Requires-Python: >=3.8,<4.0
Classifier: Programming Language :: Python :: 3
Classifier: Programming Language :: Python :: 3.8
Classifier: Programming Language :: Python :: 3.9
Classifier: Programming Language :: Python :: 3.10
Classifier: Programming Language :: Python :: 3.11
Requires-Dist: pydantic (>=1.10.2,<2.0.0)
Requires-Dist: setuptools (>=65.7.0,<66.0.0)
